{
  "activeBrandingSetId" : "29f336f5-b44b-432d-b17a-030d4309e372",
  "customCSS" : "",
  "developerName" : "stella",
  "id" : "139cbc64-131d-47d2-b179-3c60bb612518",
  "label" : "Stella",
  "layouts" : {
    "Inner" : "4dbcd7d3-3d43-4438-9492-d015a0124709",
    "Login" : "5763451b-ea3d-414d-bbbe-d6221c16d8d1"
  },
  "type" : "theme",
  "views" : [ {
    "componentAttributes" : { },
    "componentName" : "salesforceIdentity:loginBody2",
    "id" : "5763451b-ea3d-414d-bbbe-d6221c16d8d1",
    "label" : "Login",
    "regions" : [ {
      "id" : "450139a4-ee62-4eb1-a3d4-8465b8eaee80",
      "regionName" : "header",
      "type" : "region"
    }, {
      "id" : "e50d7328-511e-421c-87c3-9ce4008f600e",
      "regionName" : "content",
      "type" : "region"
    }, {
      "id" : "288c2b45-4011-4ca0-acb6-9a582d0c09d6",
      "regionName" : "footer",
      "type" : "region"
    } ],
    "type" : "view"
  }, {
    "componentAttributes" : {
      "fixedPageWidth" : 1280,
      "headerBgColor" : "rgba(0, 0, 0, 0.8)",
      "isHeaderPinned" : false,
      "isHeroUnderHeader" : false,
      "isPageWidthFixed" : true,
      "showHeader" : true,
      "showHero" : false
    },
    "componentName" : "siteforce:themeLayoutStarter",
    "id" : "4dbcd7d3-3d43-4438-9492-d015a0124709",
    "label" : "Default",
    "regions" : [ {
      "components" : [ {
        "componentAttributes" : {
          "background" : "background: #262627",
          "backgroundOverlayColor" : "rgba(0, 0, 0, 0.3)",
          "borderBottomColor" : "rgba(0, 0, 0, 0)",
          "centerAlignLogo" : false,
          "collapseNavMenu" : false,
          "containHeader" : true,
          "containHeaderWidth" : 1280,
          "dropdownBackgroundColor" : "#FFFFFF",
          "dropdownBackgroundHoverColor" : "",
          "dropdownBorderColor" : "#F0F0F0",
          "dropdownTextColor" : "",
          "dropdownTextHoverColor" : "",
          "headerHeight" : 8,
          "linkActiveBorderColor" : "",
          "linkColor" : "#FFFFFF",
          "linkHoverColor" : "rgba(255, 255, 255, 0.95)",
          "linkTextShadowColor" : "rgba(0, 0, 0, 0.8)",
          "logoWidth" : 40,
          "searchStyle" : "collapsed",
          "showAppLauncher" : false,
          "showNavMenuOnLeft" : true,
          "showNotifications" : true,
          "showProfileMenu" : true,
          "showSearch" : true
        },
        "componentName" : "forceCommunity:themeHeaderCompact",
        "id" : "8c01ce33-2088-4485-a0a7-08f1ac4579aa",
        "regions" : [ {
          "components" : [ {
            "componentAttributes" : {
              "buttonBackgroundColor" : "",
              "buttonBackgroundHoverColor" : "",
              "buttonBorderColor" : "rgba(240, 240, 240, 0)",
              "buttonBorderRadius" : 0,
              "buttonText" : "Log in",
              "buttonTextColor" : "",
              "buttonTextHoverColor" : "",
              "customizableUserProfileMenuEditor" : "Default_User_Profile_Menu",
              "menuStyleSettings" : "{\"selectedMenuStyleSetting\":\"iconOnly\",\"selectedIconSetting\":\"userAvatar\",\"includeCompanyName\":false,\"selectedTextOrientationSetting\":\"right\"}"
            },
            "componentName" : "forceCommunity:customizableUserProfileMenu",
            "id" : "c8bfc336-3090-42bb-a302-8316874d9af3",
            "renditionMap" : { },
            "type" : "component"
          } ],
          "id" : "58d66eb7-cde9-4c4a-8217-3da695d0ced7",
          "regionName" : "themeHeaderProfileMenu",
          "type" : "region"
        }, {
          "components" : [ {
            "componentAttributes" : {
              "backgroundColor" : "rgba(255, 255, 255, 0)",
              "borderColor" : "#FFFFFF",
              "borderRadius" : 0,
              "borderStyle" : "bottomborder",
              "buttonColor" : "",
              "buttonHoverColor" : "",
              "crossObjectTypeaheadApiNames" : "",
              "iconColor" : "#FFFFFF",
              "placeholderText" : "Search...",
              "placeholderTextColor" : "rgba(255, 255, 255, 0.8)",
              "showSearchButton" : false,
              "textColor" : "#FFFFFF",
              "typeaheadResultMax" : 5,
              "useTypeahead" : true
            },
            "componentName" : "forceCommunity:themeSearch",
            "id" : "fec99132-ce1a-4c4c-9421-b47d58057648",
            "renditionMap" : { },
            "type" : "component"
          } ],
          "id" : "503a0019-edc1-49a6-9416-be4424490b2f",
          "regionName" : "search",
          "type" : "region"
        }, {
          "components" : [ {
            "componentAttributes" : {
              "navAlignment" : "right",
              "navItemThreshold" : 5,
              "navigationMenuEditorRefresh" : ""
            },
            "componentName" : "forceCommunity:themeNav",
            "id" : "c1ad3669-8a19-426b-af46-9d4cf0df006e",
            "renditionMap" : { },
            "type" : "component"
          } ],
          "id" : "3db9284c-9cd5-4383-b377-81a69493702e",
          "regionName" : "nav",
          "type" : "region"
        }, {
          "id" : "a642fbde-913b-45fa-925d-989f9ee3dfe1",
          "regionName" : "cartIcon",
          "type" : "region"
        } ],
        "renditionMap" : { },
        "type" : "component"
      } ],
      "id" : "1eee6ad9-98ff-4779-aa0a-a1ee5d87c3cd",
      "regionName" : "themeHeader",
      "type" : "region"
    }, {
      "components" : [ {
        "componentAttributes" : {
          "bgImage" : "background: rgba(38,38,39,0.8)",
          "bgOverlayColor" : "rgba(0, 0, 0, 0.3)",
          "captionText" : "",
          "captionTextColor" : "#FFFFFF",
          "captionTextShadowColor" : "rgba(0, 0, 0, 0.8)",
          "contentAlignment" : "center",
          "contentWidth" : 75,
          "ctaBtnOneBgColor" : "",
          "ctaBtnOneBgHoverColor" : "",
          "ctaBtnOneBorderColor" : "rgba(255, 255, 255, 0)",
          "ctaBtnOneOpenNewTab" : false,
          "ctaBtnOneText" : "Show Me",
          "ctaBtnOneTextColor" : "",
          "ctaBtnOneTextHoverColor" : "",
          "ctaBtnOneUrl" : "",
          "ctaBtnRadius" : 4,
          "ctaBtnTwoBgColor" : "rgba(255, 255, 255, 0)",
          "ctaBtnTwoBgHoverColor" : "#FFFFFF",
          "ctaBtnTwoBorderColor" : "#FFFFFF",
          "ctaBtnTwoOpenNewTab" : false,
          "ctaBtnTwoText" : "Learn More",
          "ctaBtnTwoTextColor" : "#FFFFFF",
          "ctaBtnTwoTextHoverColor" : "#262627",
          "ctaBtnTwoUrl" : "",
          "ctaShowBtnOne" : true,
          "ctaShowBtnTwo" : false,
          "fixedHeroWidth" : true,
          "heroHeight" : 125,
          "heroWidth" : 1280,
          "showCaption" : false,
          "showSubtitle" : false,
          "showTitle" : true,
          "subtitleText" : "",
          "subtitleTextColor" : "#FFFFFF",
          "subtitleTextShadowColor" : "rgba(0, 0, 0, 0.8)",
          "titleText" : "What can we help you with?",
          "titleTextColor" : "#FFFFFF",
          "titleTextShadowColor" : "rgba(0, 0, 0, 0.8)",
          "type" : "showSearch"
        },
        "componentName" : "forceCommunity:themeHeroStarter",
        "id" : "e646c7e6-1d49-4e0d-933f-f8866ea01d6d",
        "regions" : [ {
          "components" : [ {
            "componentAttributes" : {
              "backgroundColor" : "#FFFFFF",
              "borderColor" : "#262627",
              "borderRadius" : 4,
              "borderStyle" : "outline",
              "buttonColor" : "",
              "buttonHoverColor" : "",
              "crossObjectTypeaheadApiNames" : "",
              "iconColor" : "rgba(0, 0, 0, 0.8)",
              "placeholderText" : "Ask a question...",
              "placeholderTextColor" : "rgba(0, 0, 0, 0.6)",
              "publicDropdownBackgroundColor" : "#FFFFFF",
              "publicDropdownBackgroundHoverColor" : "",
              "publicDropdownBorderColor" : "#F0F0F0",
              "publicDropdownTextColor" : "",
              "publicDropdownTextHoverColor" : "",
              "showSearchButton" : false,
              "textColor" : "rgba(0, 0, 0, 0.8)",
              "typeaheadResultMax" : 6,
              "useTypeahead" : true
            },
            "componentName" : "forceCommunity:themeSearchHero",
            "id" : "ac598d23-3f55-4a6c-9520-85ff5112d0a9",
            "renditionMap" : { },
            "type" : "component"
          } ],
          "id" : "1b342fc3-1696-49b2-b655-3fa3824c1882",
          "regionName" : "search",
          "type" : "region"
        } ],
        "renditionMap" : { },
        "type" : "component"
      } ],
      "id" : "f5edf518-1b3e-4aff-a09f-29cd7f121f98",
      "regionName" : "themeHero",
      "type" : "region"
    }, {
      "id" : "ca66a626-805a-4578-8efb-b678b981e686",
      "regionName" : "themeFooter",
      "type" : "region"
    } ],
    "type" : "view"
  } ]
}